senpwai/__init__.py
senpwai/__main__.py
senpwai/assets/audio/aqua-crying.mp3
senpwai/assets/audio/bunshin-poof.mp3
senpwai/assets/audio/gigachad.mp3
senpwai/assets/audio/kage-bunshin-no-jutsu.mp3
senpwai/assets/audio/merry-chrismasu.mp3
senpwai/assets/audio/morbin-time.mp3
senpwai/assets/audio/one-piece-real-1.mp3
senpwai/assets/audio/one-piece-real-2.mp3
senpwai/assets/audio/sen-favourite.wav
senpwai/assets/audio/toki-wa-ugoki-dasu.mp3
senpwai/assets/audio/what-da-hell.mp3
senpwai/assets/audio/za-warudo.mp3
senpwai/assets/background-images/about.jpg
senpwai/assets/background-images/chopper-crying.png
senpwai/assets/background-images/chosen-anime.jpg
senpwai/assets/background-images/christmas.jpg
senpwai/assets/background-images/downloads.png
senpwai/assets/background-images/search.jpg
senpwai/assets/background-images/settings.jpg
senpwai/assets/background-images/update.jpg
senpwai/assets/background-images/valentines.jpg
senpwai/assets/download-icons/cancel.png
senpwai/assets/download-icons/down.png
senpwai/assets/download-icons/pause.png
senpwai/assets/download-icons/resume.png
senpwai/assets/download-icons/trash.png
senpwai/assets/download-icons/up.png
senpwai/assets/link-icons/discord.png
senpwai/assets/link-icons/github-sponsors.svg
senpwai/assets/link-icons/github.png
senpwai/assets/link-icons/patreon.png
senpwai/assets/link-icons/reddit.png
senpwai/assets/mascots/1.png
senpwai/assets/mascots/2.png
senpwai/assets/misc/anime-not-found.gif
senpwai/assets/misc/folder.png
senpwai/assets/misc/loading.gif
senpwai/assets/misc/senpwai-icon.ico
senpwai/assets/misc/task-complete.png
senpwai/assets/navigation-bar-icons/about.png
senpwai/assets/navigation-bar-icons/downloads.png
senpwai/assets/navigation-bar-icons/search.png
senpwai/assets/navigation-bar-icons/settings.png
senpwai/assets/navigation-bar-icons/update.png
senpwai/assets/reviewer-profile-pics/hentai-addict.png
senpwai/assets/reviewer-profile-pics/morbius-is-peak.png
senpwai-2.1.17.dist-info/entry_points.txt
senpwai-2.1.17.dist-info/LICENSE
senpwai-2.1.17.dist-info/METADATA
senpwai-2.1.17.dist-info/WHEEL
senpwai-2.1.17.dist-info/RECORD
