Metadata-Version: 2.1
Name: senpwai
Version: 2.1.17
Summary: A desktop app for tracking and batch downloading anime
Home-page: https://github.com/SenZmaKi/Senpwai
License: GPL v3
Keywords: anime,app,cli,desktop app,anime downloader,anime cli,anime app,anime tracker,batch anime downloader,bulk anime  downloader,anime desktop app,anime tracker app
Author: SenZmaKi
Author-email: senzmaki@gmail.com
Requires-Python: >=3.11,<4.0
Classifier: License :: Other/Proprietary License
Classifier: Programming Language :: Python :: 3
Classifier: Programming Language :: Python :: 3.11
Classifier: Programming Language :: Python :: 3.12
Requires-Dist: anitopy (>=2.1.1,<3.0.0)
Requires-Dist: appdirs (>=1.4.4,<2.0.0)
Requires-Dist: argparse (>=1.4.0,<2.0.0)
Requires-Dist: bs4 (>=0.0.1,<0.0.2)
Requires-Dist: cryptography (>=41.0.7,<42.0.0)
Requires-Dist: pylnk3 (>=0.4.2,<0.5.0)
Requires-Dist: pyqt6 (>=6.6.1,<7.0.0)
Requires-Dist: requests (>=2.31.0,<3.0.0)
Requires-Dist: tqdm (>=4.66.1,<5.0.0)
Requires-Dist: yarl (>=1.9.4,<2.0.0)
Project-URL: Bug Tracker, https://github.com/SenZmaKi/Senpwai/issues
Project-URL: Documentation, https://github.com/SenZmaKi/Senpwai/blob/master/README.md
Project-URL: Discord, https://discord.gg/invite/e9UxkuyDX2
Project-URL: Repository, https://github.com/SenZmaKi/Senpwai
Project-URL: Reddit, https://www.reddit.com/r/Senpwai
